fast_auth/__init__.py
fast_auth/app_setup.py
fast_auth/constants.py
fast_auth/exceptions.py
fast_auth/funcs.py
fast_auth/logger.py
fast_auth/routes.py
fast_auth/settings.py
fast_auth/token.py
fast_auth/user.py
fast_auth_tools-0.3.1.dist-info/METADATA
fast_auth_tools-0.3.1.dist-info/WHEEL
fast_auth_tools-0.3.1.dist-info/entry_points.txt
fast_auth_tools-0.3.1.dist-info/top_level.txt
fast_auth_tools-0.3.1.dist-info/RECORD
