Metadata-Version: 2.2
Name: fast-auth-tools
Version: 0.3.1
Summary: Simple Authentication Library for FastAPI
Home-page: https://github.com/nihilok/auth_base
Author: nihilok
Author-email: nihilok@jarv.dev
Requires-Dist: fastapi
Requires-Dist: python-multipart
Requires-Dist: passlib
Requires-Dist: bcrypt==4.0.1
Requires-Dist: aiosqlite
Requires-Dist: PyJWT
Requires-Dist: pyyaml
Dynamic: author
Dynamic: author-email
Dynamic: description
Dynamic: description-content-type
Dynamic: home-page
Dynamic: requires-dist
Dynamic: summary
